driven_sql_tool/__init__.py
driven_sql_tool-0.1.1.dist-info/METADATA
driven_sql_tool-0.1.1.dist-info/WHEEL
driven_sql_tool-0.1.1.dist-info/licenses/LICENSE
driven_sql_tool-0.1.1.dist-info/RECORD
