Metadata-Version: 2.4
Name: driven_sql_tool
Version: 0.1.1
Summary: Simple wrapper (based on turbodbc) for most common MSSQL operations I face day-to-day
Author-email: Ilya Davydov <shaddam.jabbar@gmail.com>
License-File: LICENSE
Classifier: License :: OSI Approved :: MIT License
Classifier: Operating System :: OS Independent
Classifier: Programming Language :: Python :: 3
Requires-Python: >=3.11
Requires-Dist: joblib>=1.4
Requires-Dist: pandas>=2.2
Requires-Dist: turbodbc>=5.0
